graph_diffusers/__init__.py
graph_diffusers/_extras.py
graph_diffusers/_typing.py
graph_diffusers/_utils.py
graph_diffusers/_version.py
graph_diffusers/io/__init__.py
graph_diffusers/io/torch.py
graph_diffusers/models.py
graph_diffusers/operators.py
graph_diffusers/py.typed
graph_diffusers-0.1.0.dist-info/LICENSE
graph_diffusers-0.1.0.dist-info/METADATA
graph_diffusers-0.1.0.dist-info/WHEEL
graph_diffusers-0.1.0.dist-info/RECORD
